fenics_smart-2.3.0.dist-info/licenses/LICENSE
smart/__init__.py
smart/common.py
smart/config.py
smart/deprecation.py
smart/mesh.py
smart/mesh_tools.py
smart/model.py
smart/model_assembly.py
smart/solvers.py
smart/units.py
smart/utils.py
smart/visualization.py
fenics_smart-2.3.0.dist-info/METADATA
fenics_smart-2.3.0.dist-info/WHEEL
fenics_smart-2.3.0.dist-info/top_level.txt
fenics_smart-2.3.0.dist-info/RECORD
