Metadata-Version: 2.4
Name: fenics-smart
Version: 2.3.0
Summary: Spatial Modeling Algorithms for Reactions and Transport (SMART) is a high-performance finite-element-based simulation package for model specification and numerical simulation of spatially-varying reaction-transport processes in biological cells.
Author-email: Justin Laughlin <justinglaughlin@gmail.com>
License: GNU LESSER GENERAL PUBLIC LICENSE
Project-URL: homepage, https://rangamanilabucsd.github.io/smart
Project-URL: repository, https://github.com/RangamaniLabUCSD/smart
Requires-Python: >=3.8
License-File: LICENSE
Requires-Dist: numpy<2.0,>=1.16.0
Requires-Dist: pandas
Requires-Dist: Pint
Requires-Dist: scipy>=1.1.0
Requires-Dist: sympy
Requires-Dist: cached-property
Requires-Dist: tabulate
Requires-Dist: termcolor
Provides-Extra: test
Requires-Dist: pytest; extra == "test"
Requires-Dist: pytest-cov; extra == "test"
Provides-Extra: docs
Requires-Dist: jupyter-book==0.15.1; extra == "docs"
Requires-Dist: sphinx-autoapi==2.0.1; extra == "docs"
Requires-Dist: astroid<3; extra == "docs"
Provides-Extra: examples
Requires-Dist: meshio; extra == "examples"
Requires-Dist: gmsh; extra == "examples"
Requires-Dist: matplotlib; extra == "examples"
Requires-Dist: jupyter; extra == "examples"
Requires-Dist: jupyterlab; extra == "examples"
Provides-Extra: pyvista
Requires-Dist: pyvista[all]>=0.43.0; extra == "pyvista"
Requires-Dist: trame-vuetify; extra == "pyvista"
Requires-Dist: ipywidgets; extra == "pyvista"
Provides-Extra: all
Requires-Dist: fenics-smart[examples]; extra == "all"
Requires-Dist: fenics-smart[test]; extra == "all"
Requires-Dist: fenics-smart[docs]; extra == "all"
Requires-Dist: fenics-smart[pyvista]; extra == "all"
Dynamic: license-file
